keyring_proxy/__init__.py
keyring_proxy/_version.py
keyring_proxy/backend.py
keyring_proxy/connection.py
keyring_proxy/packets.py
keyring_proxy/py.typed
keyring_proxy/socketproxy.py
keyring_proxy/stdioproxy.py
keyring_proxy/transport.py
keyring_proxy-0.2.31.1.dist-info/METADATA
keyring_proxy-0.2.31.1.dist-info/WHEEL
keyring_proxy-0.2.31.1.dist-info/RECORD
