Metadata-Version: 2.4
Name: keyring-proxy
Version: 0.2.31.1
Summary: Proxy Base for pypi keyring
Project-URL: Repository, https://github.com/KalleDK/py-keyring-proxy
Author-email: "Kalle M. Aagaard" <git@k-moeller.dk>
License: MIT
Requires-Python: >=3.12
Requires-Dist: keyring>=25.5.0
Requires-Dist: pydantic>=2.9.2
